mcp_server_opensearch/__init__.py
mcp_server_opensearch/__main__.py
mcp_server_opensearch/sse_server.py
mcp_server_opensearch/stdio_server.py
opensearch/__init__.py
opensearch/client.py
opensearch/helper.py
test_opensearch_mcp-0.1.3.dist-info/licenses/LICENSE
tools/__init__.py
tools/tools.py
test_opensearch_mcp-0.1.3.dist-info/METADATA
test_opensearch_mcp-0.1.3.dist-info/WHEEL
test_opensearch_mcp-0.1.3.dist-info/entry_points.txt
test_opensearch_mcp-0.1.3.dist-info/top_level.txt
test_opensearch_mcp-0.1.3.dist-info/RECORD
